HISTORY.rst
LICENSE
MANIFEST.in
README.rst
setup.py
djangocms_stacks.egg-info/PKG-INFO
djangocms_stacks.egg-info/SOURCES.txt
djangocms_stacks.egg-info/dependency_links.txt
djangocms_stacks.egg-info/not-zip-safe
djangocms_stacks.egg-info/requires.txt
djangocms_stacks.egg-info/top_level.txt
stacks/__init__.py
stacks/admin.py
stacks/cms_plugins.py
stacks/fields.py
stacks/models.py
stacks/locale/de/LC_MESSAGES/django.po
stacks/locale/en/LC_MESSAGES/django.po
stacks/migrations/0001_initial.py
stacks/migrations/__init__.py
stacks/templates/admin/stacks/stack/change_form.html
stacks/templates/cms/plugins/stacks.html
stacks/templatetags/__init__.py
stacks/templatetags/stack_tags.py