Metadata-Version: 1.1
Name: djangocms-stacks
Version: 0.2.2
Summary: Stacks: Re-usable content blocks in django CMS.
Home-page: http://github.com/divio/djangocms-stacks
Author: Divio AG
Author-email: developers@divio.ch
License: BSD
Platform: OS Independent
Classifier: Development Status :: 4 - Beta
Classifier: Framework :: Django
Classifier: Intended Audience :: Developers
Classifier: License :: OSI Approved :: BSD License
Classifier: Operating System :: OS Independent
Classifier: Programming Language :: Python
Classifier: Topic :: Internet :: WWW/HTTP
